pygennaro/__init__.py
pygennaro/commandline.py
pygennaro/encoder.py
pygennaro/genstring.py
pygennaro/grammar.py
pygennaro/rules.py
pygennaro-0.1.0.dist-info/entry_points.txt
pygennaro-0.1.0.dist-info/WHEEL
pygennaro-0.1.0.dist-info/METADATA
pygennaro-0.1.0.dist-info/RECORD
